Workbook

Sheet Assumptions
A1: RGTI — DCF Model Assumptions
A2: All dollar inputs in $thousands | Blue = input | Black = formula | Yellow = key assumption
A4: A. HISTORICAL FINANCIAL DATA (Source: RGTI 10-K FY2025, SEC EDGAR CIK 0001838359)
A5: Line Item | B5: FY2023 | C5: FY2024 | D5: FY2025 | E5: Notes
A6: Revenue | B6: 12008 | C6: 10790 | D6: 7088 | E6: EDGAR RevenueFromContractWithCustomerIncludingAssessedTax
A7: Cost of Revenue | B7: 2800 | C7: 5093 | D7: 5024 | E7: EDGAR CostOfRevenue
A8: Gross Profit ($000s) | B8: =B6-B7 | C8: =C6-C7 | D8: =D6-D7 | E8: Formula: Revenue − CoR
A9: Gross Margin % | B9: =B8/B6 | C9: =C8/C6 | D9: =D8/D6 | E9: Formula
A10: SG&A | B10: 27744 | C10: 24457 | D10: 25379 | E10: EDGAR GeneralAndAdministrativeExpense
A11: R&D | B11: 52768 | C11: 49750 | D11: 61345 | E11: EDGAR ResearchAndDevelopmentExpense
A12: EBIT (Operating Loss) | B12: -72295 | C12: -68510 | D12: -84660 | E12: EDGAR OperatingIncomeLoss
A13: D&A | B13: 7400 | C13: 6900 | D13: 8100 | E13: EDGAR DepreciationDepletionAndAmortization (cash-flow stmt)
A14: Stock-Based Comp | B14: 12409 | C14: 13069 | D14: 17605 | E14: EDGAR AllocatedShareBasedCompensationExpense
A15: CapEx (PP&E) | B15: 9059 | C15: 11098 | D15: 18676 | E15: EDGAR PaymentsToAcquirePropertyPlantAndEquipment
A16: Capitalized Software | B16: 0 | C16: 0 | D16: 0 | E16: Source: EDGAR
A17: Interest Expense | B17: 5779 | C17: 0 | D17: 0 | E17: EDGAR InterestExpense (0 in FY2024/25 — debt fully retired)
A18: Interest Income | B18: 0 | C18: 0 | D18: 0 | E18: Not separately tagged in XBRL
A19: Net Loss | B19: -75107 | C19: -200988 | D19: -216210 | E19: EDGAR NetIncomeLoss
A22: A2. BALANCE SHEET SNAPSHOT (Source: RGTI 10-K FY2025, SEC EDGAR CIK 0001838359)
A23: Line Item | B23: FY2024 | C23: FY2025 | E23: Notes
A24: Cash & Equivalents | B24: 67674 | C24: 44851 | E24: EDGAR Cash
A25: AFS Investments (Current) | B25: 0 | C25: 0 | E25: EDGAR / 0 if none
A26: AFS Investments (Non-Current) | B26: 0 | C26: 0 | E26: EDGAR / 0 if none
A27: Total Liquidity | B27: =B24+B25+B26 | C27: =C24+C25+C26 | E27: Formula: Cash + AFS
A28: Accounts Receivable | B28: 2427 | C28: 2551 | E28: EDGAR AR
A29: Goodwill | B29: 0 | C29: 0 | E29: EDGAR Goodwill
A30: Intangibles, net | B30: 0 | C30: 0 | E30: EDGAR Intangibles
A31: Total Debt (Gross Principal) | B31: 0 | C31: 0 | E31: EDGAR Debt
A32: Post-FY2025 Debt | B32: =B31 | C32: 0 | E32: Debt-free as of FY2024; term loan fully retired
A33: Shares Outstanding | B33: 184666000 | C33: 309763000 | E33: EDGAR diluted shares
A34: Shares Used in Bridge | B34: =B33 | C34: 309763000 | E34: FY2025 diluted wtd-avg (significant ongoing dilution expected)
A35: Federal NOL Carryforward ($K) | C35: 131826 | E35: EDGAR DeferredTaxAssetsGross FY2025 ($K proxy for NOL)
A38: B. REVENUE GROWTH ASSUMPTIONS (Yellow = key input)
A39: Assumption | B39: Base Case | C39: Bull Case | D39: Bear Case | E39: Notes
A40: FY2026 Revenue Growth Rate | B40: 0.5 | C40: 1 | D40: -0.1 | E40: Revenue declining in FY2025; stabilisation + first commercial ramp
A41: FY2027 Revenue Growth Rate | B41: 0.8 | C41: 2 | D41: 0.1 | E41: Quantum advantage demonstrations driving enterprise pilots
A42: FY2028 Revenue Growth Rate | B42: 1.2 | C42: 2.5 | D42: 0.2 | E42: Multi-qubit systems reaching commercial-grade fidelity
A43: FY2029 Revenue Growth Rate | B43: 1 | C43: 2 | D43: 0.3 | E43: Hyperscaler + pharma / finance contract wins
A44: FY2030 Revenue Growth Rate | B44: 0.8 | C44: 1.5 | D44: 0.25 | E44: TAM penetration; Rigetti platform-as-a-service scaling
A45: FY2031–2035 Revenue Growth Rate | B45: 0.6 | C45: 1 | D45: 0.18 | E45: Quantum-classical hybrid workloads mainstream
A46: FY2036–2040 Revenue Growth Rate | B46: 0.35 | C46: 0.6 | D46: 0.1
A47: FY2041–2045 Revenue Growth Rate | B47: 0.15 | C47: 0.25 | D47: 0.07
A49: ACTIVE SCENARIO → Enter 1 = Base Case | 2 = Bull Case | 3 = Bear Case
A50: Active Scenario (1/2/3) | B50: 1 | E50: Change this cell to switch scenarios on DCF sheet. 1=Base, 2=Bull, 3=Bear
A52: C. MARGIN & COST ASSUMPTIONS
A53: Assumption | B53: Base Case | C53: Bull Case | D53: Bear Case | E53: Notes
A54: Gross Margin % — FY2026 | B54: 0.32 | C54: 0.42 | D54: 0.2 | E54: FY2025=29%; hardware-heavy mix; software shift begins
A55: Gross Margin % — FY2027 | B55: 0.45 | C55: 0.6 | D55: 0.25
A56: Gross Margin % — FY2028 | B56: 0.55 | C56: 0.68 | D56: 0.3
A57: Gross Margin % — FY2029 | B57: 0.62 | C57: 0.72 | D57: 0.35
A58: Gross Margin % — FY2030 | B58: 0.65 | C58: 0.74 | D58: 0.4
A59: Gross Margin % — FY2031–35 | B59: 0.68 | C59: 0.76 | D59: 0.45
A60: Gross Margin % — FY2036–45 | B60: 0.7 | C60: 0.78 | D60: 0.5
A61: SG&A as % Revenue — FY2026 | B61: 2.2 | C61: 1.4 | D61: 3.1 | E61: FY2025 SGA/Rev=358%; absolute SGA ~$25M semi-fixed
A62: SG&A as % Revenue — FY2027 | B62: 1.1 | C62: 0.65 | D62: 2.4
A63: SG&A as % Revenue — FY2028 | B63: 0.58 | C63: 0.38 | D63: 1.4
A64: SG&A as % Revenue — FY2029 | B64: 0.35 | C64: 0.22 | D64: 0.85
A65: SG&A as % Revenue — FY2030 | B65: 0.24 | C65: 0.16 | D65: 0.55
A66: SG&A as % Revenue — FY2031–35 | B66: 0.17 | C66: 0.12 | D66: 0.35
A67: SG&A as % Revenue — FY2036–45 | B67: 0.12 | C67: 0.08 | D67: 0.26
A68: R&D as % Revenue — All Years | B68: 0.45 | C68: 0.35 | D68: 0.55 | E68: FY2025 R&D/Rev=866%; declines as rev scales
A69: D&A as % Revenue — All Years | B69: 0.45 | C69: 0.38 | D69: 0.52 | E69: FY2025 DA/Rev=114%; reflects quantum hardware depreciation
A70: CapEx as % Revenue — All Years | B70: 0.15 | C70: 0.1 | D70: 0.2 | E70: FY2025=263% of tiny revenue; quantum system capex
A71: Stock-Based Comp as % Revenue | B71: 0.12 | C71: 0.1 | D71: 0.15 | E71: FY2025 SBC=$17.6M; normalising as rev grows
A72: Change in NWC as % Rev Change | B72: 0.03 | C72: 0.02 | D72: 0.05
A73: Tax Rate (Cash) | B73: 0 | C73: 0 | D73: 0 | E73: $132M DTA; NOL shields all near-term income
A74: Tax Rate (Terminal / WACC) | B74: 0.21 | C74: 0.21 | D74: 0.21 | E74: US statutory rate
A77: D. WACC ASSUMPTIONS
A78: Assumption | B78: Base Case | C78: Bull Case | D78: Bear Case | E78: Notes
A79: Risk-Free Rate | B79: 0.043 | C79: 0.04 | D79: 0.046 | E79: 10-yr US Treasury May 2026
A80: Equity Risk Premium | B80: 0.055 | C80: 0.05 | D80: 0.06 | E80: Damodaran US ERP
A81: Beta (Levered) | B81: 2.5 | C81: 2 | D81: 3 | E81: Deep-tech pre-revenue; quantum binary outcome; ~2.5–3.0 beta
A82: Size / Illiquidity Premium | B82: 0.035 | C82: 0.02 | D82: 0.05
A83: Cost of Equity | B83: =B79+B81*B80+B82 | C83: =C79+C81*C80+C82 | D83: =D79+D81*D80+D82 | E83: Formula: Rf + Beta×ERP + Size
A84: Pre-Tax Cost of Debt | B84: 0.05 | C84: 0.045 | D84: 0.065 | E84: No current debt; modelled for future capital raises
A85: Weight of Equity | B85: 0.9 | C85: 0.95 | D85: 0.85 | E85: Equity-funded; may issue convertibles for quantum hardware buildout
A86: Weight of Debt | B86: =1-B85 | C86: =1-C85 | D86: =1-D85 | E86: Formula: 1 − Weight of Equity
A87: WACC | B87: =B83*B85+B84*(1-D74)*B86 | C87: =C83*C85+C84*(1-D74)*C86 | D87: =D83*D85+D84*(1-D74)*D86 | E87: Formula: Ke×We + Kd×(1−t)×Wd
A90: E. TERMINAL VALUE ASSUMPTIONS
A91: Assumption | B91: Base Case | C91: Bull Case | D91: Bear Case | E91: Notes
A92: Terminal Growth Rate (Gordon Growth) | B92: 0.035 | C92: 0.045 | D92: 0.02 | E92: Quantum-AI platform; long-run GDP+ growth if commercialised
A93: Terminal EV/EBITDA Multiple (cross-check) | B93: 25 | C93: 40 | D93: 8 | E93: Quantum platform comps: 20–50× if winner; 5–10× if niche
A94: Terminal EBITDA Margin (for EV/EBITDA check) | B94: 0.2 | C94: 0.35 | D94: 0.05 | E94: Requires platform shift; highly binary
A97: F. WACC DECOMPOSITION — Why WACC is high & the two levers to lower it
A98: Component | B98: Current Value | C98: Source / Formula | D98: Contribution to WACC | E98: How to Lower It
A99: Risk-Free Rate (Rf) | B99: =B79 | C99: Rf × We | D99: =B79*B85
A100: Equity Risk Premium (ERP) | B100: =B80 | C100: Damodaran ERP | D100: =B81*B80*B85
A101: Beta ← #1 LEVER | B101: =B81 | C101: Levered beta | D101: =B81*B80*B85
A102: Size/Illiquidity ← #2 | B102: =B82 | C102: Premium | D102: =B82*B85
A103: Cost of Equity (Ke) | B103: =B83 | C103: Rf+Beta×ERP+Size | D103: =B83*B85
A104: Cost of Debt (Kd after-tax) | B104: =B84 | C104: Pre-tax × (1-t) | D104: =B84*(1-D74)*B86
A105: WACC | B105: =B87 | C105: Formula result
A107: G. WACC COMPRESSION ROADMAP — Change Beta (row 81) and Size Premium (row 82) to model each stage
A108: Stage | B108: Beta | C108: Size Premium | D108: Implied WACC | E108: Trigger / Condition
A109: Current Base Case | B109: =B81 | C109: =B82 | D109: =B87 | E109: Pre-profit baseline
A110: Stage 1 — First Revenue Scale ($50M) | B110: 1.8 | C110: 0.025 | D110: =(B79+1.8*B80+0.025)*B85+B84*(1-D74)*B86 | E110: Recurring quantum-cloud ARR materialises
A111: Stage 2 — Break-Even Proof | B111: 1.4 | C111: 0.015 | D111: =(B79+1.4*B80+0.015)*B85+B84*(1-D74)*B86 | E111: FCF-positive; quantum-error-correction milestone
A112: Stage 3 — Hyperscaler Partnerships | B112: 1.1 | C112: 0.005 | D112: =(B79+1.1*B80+0.005)*B85+B84*(1-D74)*B86 | E112: AWS/Azure/GCP embedded quantum layer
A113: Blue Sky — Quantum Category Leader | B113: 0.8 | C113: 0 | D113: =(B79+0.8*B80+0.0)*B85+B84*(1-D74)*B86 | E113: De-facto standard for quantum computing infra

Sheet DCF Model
A1: RGTI — 20-Year Unlevered Free Cash Flow DCF Model
A2: =IF(Assumptions!B50=1,"▶ ACTIVE: BASE CASE",IF(Assumptions!B50=2,"▶ ACTIVE: BULL CASE","▶ ACTIVE: BEAR CASE"))
A3: Year | B3: FY2025 (Actual) | C3: 2026 | D3: 2027 | E3: 2028 | F3: 2029 | G3: 2030 | H3: 2031 | I3: 2032 | J3: 2033 | K3: 2034 | L3: 2035 | M3: 2036 | N3: 2037 | O3: 2038 | P3: 2039 | Q3: 2040 | R3: 2041 | S3: 2042 | T3: 2043 | U3: 2044 | V3: 2045
A4: A. REVENUE PROJECTION
A5: Revenue Growth Rate (Active Scenario) | B5: — | C5: =CHOOSE(Assumptions!B50,Assumptions!B40,Assumptions!C40,Assumptions!D40) | D5: =CHOOSE(Assumptions!B50,Assumptions!B41,Assumptions!C41,Assumptions!D41) | E5: =CHOOSE(Assumptions!B50,Assumptions!B42,Assumptions!C42,Assumptions!D42) | F5: =CHOOSE(Assumptions!B50,Assumptions!B43,Assumptions!C43,Assumptions!D43) | G5: =CHOOSE(Assumptions!B50,Assumptions!B44,Assumptions!C44,Assumptions!D44) | H5: =CHOOSE(Assumptions!B50,Assumptions!B45,Assumptions!C45,Assumptions!D45) | I5: =CHOOSE(Assumptions!B50,Assumptions!B45,Assumptions!C45,Assumptions!D45) | J5: =CHOOSE(Assumptions!B50,Assumptions!B45,Assumptions!C45,Assumptions!D45) | K5: =CHOOSE(Assumptions!B50,Assumptions!B45,Assumptions!C45,Assumptions!D45) | L5: =CHOOSE(Assumptions!B50,Assumptions!B45,Assumptions!C45,Assumptions!D45) | M5: =CHOOSE(Assumptions!B50,Assumptions!B46,Assumptions!C46,Assumptions!D46) | N5: =CHOOSE(Assumptions!B50,Assumptions!B46,Assumptions!C46,Assumptions!D46) | O5: =CHOOSE(Assumptions!B50,Assumptions!B46,Assumptions!C46,Assumptions!D46) | P5: =CHOOSE(Assumptions!B50,Assumptions!B46,Assumptions!C46,Assumptions!D46) | Q5: =CHOOSE(Assumptions!B50,Assumptions!B46,Assumptions!C46,Assumptions!D46) | R5: =CHOOSE(Assumptions!B50,Assumptions!B47,Assumptions!C47,Assumptions!D47) | S5: =CHOOSE(Assumptions!B50,Assumptions!B47,Assumptions!C47,Assumptions!D47) | T5: =CHOOSE(Assumptions!B50,Assumptions!B47,Assumptions!C47,Assumptions!D47) | U5: =CHOOSE(Assumptions!B50,Assumptions!B47,Assumptions!C47,Assumptions!D47) | V5: =CHOOSE(Assumptions!B50,Assumptions!B47,Assumptions!C47,Assumptions!D47)
A6: Revenue ($000s) | B6: =Assumptions!D6 | C6: =B6*(1+C5) | D6: =C6*(1+D5) | E6: =D6*(1+E5) | F6: =E6*(1+F5) | G6: =F6*(1+G5) | H6: =G6*(1+H5) | I6: =H6*(1+I5) | J6: =I6*(1+J5) | ... V6: =U6*(1+V5)
A7: B. INCOME STATEMENT PROJECTION
A8: Gross Margin % | B8: =Assumptions!D9 | C8: =CHOOSE(Assumptions!B50,Assumptions!B54,Assumptions!C54,Assumptions!D54) | D8: =CHOOSE(Assumptions!B50,Assumptions!B55,Assumptions!C55,Assumptions!D55) | E8: =CHOOSE(Assumptions!B50,Assumptions!B56,Assumptions!C56,Assumptions!D56) | F8: =CHOOSE(Assumptions!B50,Assumptions!B57,Assumptions!C57,Assumptions!D57) | G8: =CHOOSE(Assumptions!B50,Assumptions!B58,Assumptions!C58,Assumptions!D58) | H8: =CHOOSE(Assumptions!B50,Assumptions!B59,Assumptions!C59,Assumptions!D59) | I8: =CHOOSE(Assumptions!B50,Assumptions!B59,Assumptions!C59,Assumptions!D59) | J8: =CHOOSE(Assumptions!B50,Assumptions!B59,Assumptions!C59,Assumptions!D59) | K8: =CHOOSE(Assumptions!B50,Assumptions!B59,Assumptions!C59,Assumptions!D59) | L8: =CHOOSE(Assumptions!B50,Assumptions!B59,Assumptions!C59,Assumptions!D59) | M8: =CHOOSE(Assumptions!B50,Assumptions!B60,Assumptions!C60,Assumptions!D60) | N8: =CHOOSE(Assumptions!B50,Assumptions!B60,Assumptions!C60,Assumptions!D60) | O8: =CHOOSE(Assumptions!B50,Assumptions!B60,Assumptions!C60,Assumptions!D60) | P8: =CHOOSE(Assumptions!B50,Assumptions!B60,Assumptions!C60,Assumptions!D60) | Q8: =CHOOSE(Assumptions!B50,Assumptions!B60,Assumptions!C60,Assumptions!D60) | R8: =CHOOSE(Assumptions!B50,Assumptions!B60,Assumptions!C60,Assumptions!D60) | S8: =CHOOSE(Assumptions!B50,Assumptions!B60,Assumptions!C60,Assumptions!D60) | T8: =CHOOSE(Assumptions!B50,Assumptions!B60,Assumptions!C60,Assumptions!D60) | U8: =CHOOSE(Assumptions!B50,Assumptions!B60,Assumptions!C60,Assumptions!D60) | V8: =CHOOSE(Assumptions!B50,Assumptions!B60,Assumptions!C60,Assumptions!D60)
A9: Gross Profit ($000s) | B9: =Assumptions!D8 | C9: =C6*C8 | D9: =D6*D8 | E9: =E6*E8 | F9: =F6*F8 | G9: =G6*G8 | H9: =H6*H8 | I9: =I6*I8 | J9: =J6*J8 | ... V9: =V6*V8
A10: SG&A as % Revenue | B10: =Assumptions!D10/Assumptions!D6 | C10: =CHOOSE(Assumptions!B50,Assumptions!B61,Assumptions!C61,Assumptions!D61) | D10: =CHOOSE(Assumptions!B50,Assumptions!B62,Assumptions!C62,Assumptions!D62) | E10: =CHOOSE(Assumptions!B50,Assumptions!B63,Assumptions!C63,Assumptions!D63) | F10: =CHOOSE(Assumptions!B50,Assumptions!B64,Assumptions!C64,Assumptions!D64) | G10: =CHOOSE(Assumptions!B50,Assumptions!B65,Assumptions!C65,Assumptions!D65) | H10: =CHOOSE(Assumptions!B50,Assumptions!B66,Assumptions!C66,Assumptions!D66) | I10: =CHOOSE(Assumptions!B50,Assumptions!B66,Assumptions!C66,Assumptions!D66) | J10: =CHOOSE(Assumptions!B50,Assumptions!B66,Assumptions!C66,Assumptions!D66) | K10: =CHOOSE(Assumptions!B50,Assumptions!B66,Assumptions!C66,Assumptions!D66) | L10: =CHOOSE(Assumptions!B50,Assumptions!B66,Assumptions!C66,Assumptions!D66) | M10: =CHOOSE(Assumptions!B50,Assumptions!B67,Assumptions!C67,Assumptions!D67) | N10: =CHOOSE(Assumptions!B50,Assumptions!B67,Assumptions!C67,Assumptions!D67) | O10: =CHOOSE(Assumptions!B50,Assumptions!B67,Assumptions!C67,Assumptions!D67) | P10: =CHOOSE(Assumptions!B50,Assumptions!B67,Assumptions!C67,Assumptions!D67) | Q10: =CHOOSE(Assumptions!B50,Assumptions!B67,Assumptions!C67,Assumptions!D67) | R10: =CHOOSE(Assumptions!B50,Assumptions!B67,Assumptions!C67,Assumptions!D67) | S10: =CHOOSE(Assumptions!B50,Assumptions!B67,Assumptions!C67,Assumptions!D67) | T10: =CHOOSE(Assumptions!B50,Assumptions!B67,Assumptions!C67,Assumptions!D67) | U10: =CHOOSE(Assumptions!B50,Assumptions!B67,Assumptions!C67,Assumptions!D67) | V10: =CHOOSE(Assumptions!B50,Assumptions!B67,Assumptions!C67,Assumptions!D67)
A11: SG&A ($000s) | B11: =Assumptions!D10 | C11: =C6*C10 | D11: =D6*D10 | E11: =E6*E10 | F11: =F6*F10 | G11: =G6*G10 | H11: =H6*H10 | I11: =I6*I10 | J11: =J6*J10 | ... V11: =V6*V10
A12: R&D as % Revenue | B12: =Assumptions!D11/Assumptions!D6 | C12: =CHOOSE(Assumptions!B50,Assumptions!B68,Assumptions!C68,Assumptions!D68) | D12: =CHOOSE(Assumptions!B50,Assumptions!B68,Assumptions!C68,Assumptions!D68) | E12: =CHOOSE(Assumptions!B50,Assumptions!B68,Assumptions!C68,Assumptions!D68) | F12: =CHOOSE(Assumptions!B50,Assumptions!B68,Assumptions!C68,Assumptions!D68) | G12: =CHOOSE(Assumptions!B50,Assumptions!B68,Assumptions!C68,Assumptions!D68) | H12: =CHOOSE(Assumptions!B50,Assumptions!B68,Assumptions!C68,Assumptions!D68) | I12: =CHOOSE(Assumptions!B50,Assumptions!B68,Assumptions!C68,Assumptions!D68) | J12: =CHOOSE(Assumptions!B50,Assumptions!B68,Assumptions!C68,Assumptions!D68) | K12: =CHOOSE(Assumptions!B50,Assumptions!B68,Assumptions!C68,Assumptions!D68) | L12: =CHOOSE(Assumptions!B50,Assumptions!B68,Assumptions!C68,Assumptions!D68) | M12: =CHOOSE(Assumptions!B50,Assumptions!B68,Assumptions!C68,Assumptions!D68) | N12: =CHOOSE(Assumptions!B50,Assumptions!B68,Assumptions!C68,Assumptions!D68) | O12: =CHOOSE(Assumptions!B50,Assumptions!B68,Assumptions!C68,Assumptions!D68) | P12: =CHOOSE(Assumptions!B50,Assumptions!B68,Assumptions!C68,Assumptions!D68) | Q12: =CHOOSE(Assumptions!B50,Assumptions!B68,Assumptions!C68,Assumptions!D68) | R12: =CHOOSE(Assumptions!B50,Assumptions!B68,Assumptions!C68,Assumptions!D68) | S12: =CHOOSE(Assumptions!B50,Assumptions!B68,Assumptions!C68,Assumptions!D68) | T12: =CHOOSE(Assumptions!B50,Assumptions!B68,Assumptions!C68,Assumptions!D68) | U12: =CHOOSE(Assumptions!B50,Assumptions!B68,Assumptions!C68,Assumptions!D68) | V12: =CHOOSE(Assumptions!B50,Assumptions!B68,Assumptions!C68,Assumptions!D68)
A13: R&D ($000s) | B13: =Assumptions!D11 | C13: =C6*C12 | D13: =D6*D12 | E13: =E6*E12 | F13: =F6*F12 | G13: =G6*G12 | H13: =H6*H12 | I13: =I6*I12 | J13: =J6*J12 | ... V13: =V6*V12
A14: EBIT ($000s) | B14: =Assumptions!D12 | C14: =C9-C11-C13 | D14: =D9-D11-D13 | E14: =E9-E11-E13 | F14: =F9-F11-F13 | G14: =G9-G11-G13 | H14: =H9-H11-H13 | I14: =I9-I11-I13 | J14: =J9-J11-J13 | ... V14: =V9-V11-V13
A15: EBIT Margin % | B15: =Assumptions!D12/Assumptions!D6 | C15: =C14/C6 | D15: =D14/D6 | E15: =E14/E6 | F15: =F14/F6 | G15: =G14/G6 | H15: =H14/H6 | I15: =I14/I6 | J15: =J14/J6 | ... V15: =V14/V6
A16: Cash Tax Rate (Active Scenario) | B16: =0 | C16: =CHOOSE(Assumptions!B50,Assumptions!B73,Assumptions!C73,Assumptions!D73) | D16: =CHOOSE(Assumptions!B50,Assumptions!B73,Assumptions!C73,Assumptions!D73) | E16: =CHOOSE(Assumptions!B50,Assumptions!B73,Assumptions!C73,Assumptions!D73) | F16: =CHOOSE(Assumptions!B50,Assumptions!B73,Assumptions!C73,Assumptions!D73) | G16: =CHOOSE(Assumptions!B50,Assumptions!B73,Assumptions!C73,Assumptions!D73) | H16: =CHOOSE(Assumptions!B50,Assumptions!B73,Assumptions!C73,Assumptions!D73) | I16: =CHOOSE(Assumptions!B50,Assumptions!B73,Assumptions!C73,Assumptions!D73) | J16: =CHOOSE(Assumptions!B50,Assumptions!B73,Assumptions!C73,Assumptions!D73) | K16: =CHOOSE(Assumptions!B50,Assumptions!B73,Assumptions!C73,Assumptions!D73) | L16: =CHOOSE(Assumptions!B50,Assumptions!B73,Assumptions!C73,Assumptions!D73) | M16: =CHOOSE(Assumptions!B50,Assumptions!B73,Assumptions!C73,Assumptions!D73) | N16: =CHOOSE(Assumptions!B50,Assumptions!B73,Assumptions!C73,Assumptions!D73) | O16: =CHOOSE(Assumptions!B50,Assumptions!B73,Assumptions!C73,Assumptions!D73) | P16: =CHOOSE(Assumptions!B50,Assumptions!B73,Assumptions!C73,Assumptions!D73) | Q16: =CHOOSE(Assumptions!B50,Assumptions!B73,Assumptions!C73,Assumptions!D73) | R16: =CHOOSE(Assumptions!B50,Assumptions!B73,Assumptions!C73,Assumptions!D73) | S16: =CHOOSE(Assumptions!B50,Assumptions!B73,Assumptions!C73,Assumptions!D73) | T16: =CHOOSE(Assumptions!B50,Assumptions!B73,Assumptions!C73,Assumptions!D73) | U16: =CHOOSE(Assumptions!B50,Assumptions!B73,Assumptions!C73,Assumptions!D73) | V16: =CHOOSE(Assumptions!B50,Assumptions!B73,Assumptions!C73,Assumptions!D73)
A17: NOPAT = EBIT × (1 − Tax Rate) ($000s) | B17: =B14*(1-B16) | C17: =C14*(1-C16) | D17: =D14*(1-D16) | E17: =E14*(1-E16) | F17: =F14*(1-F16) | G17: =G14*(1-G16) | H17: =H14*(1-H16) | I17: =I14*(1-I16) | ... V17: =V14*(1-V16)
A18: C. UNLEVERED FREE CASH FLOW BUILD
A19: D&A as % Revenue | B19: =Assumptions!D13/Assumptions!D6 | C19: =CHOOSE(Assumptions!B50,Assumptions!B69,Assumptions!C69,Assumptions!D69) | D19: =CHOOSE(Assumptions!B50,Assumptions!B69,Assumptions!C69,Assumptions!D69) | E19: =CHOOSE(Assumptions!B50,Assumptions!B69,Assumptions!C69,Assumptions!D69) | F19: =CHOOSE(Assumptions!B50,Assumptions!B69,Assumptions!C69,Assumptions!D69) | G19: =CHOOSE(Assumptions!B50,Assumptions!B69,Assumptions!C69,Assumptions!D69) | H19: =CHOOSE(Assumptions!B50,Assumptions!B69,Assumptions!C69,Assumptions!D69) | I19: =CHOOSE(Assumptions!B50,Assumptions!B69,Assumptions!C69,Assumptions!D69) | J19: =CHOOSE(Assumptions!B50,Assumptions!B69,Assumptions!C69,Assumptions!D69) | K19: =CHOOSE(Assumptions!B50,Assumptions!B69,Assumptions!C69,Assumptions!D69) | L19: =CHOOSE(Assumptions!B50,Assumptions!B69,Assumptions!C69,Assumptions!D69) | M19: =CHOOSE(Assumptions!B50,Assumptions!B69,Assumptions!C69,Assumptions!D69) | N19: =CHOOSE(Assumptions!B50,Assumptions!B69,Assumptions!C69,Assumptions!D69) | O19: =CHOOSE(Assumptions!B50,Assumptions!B69,Assumptions!C69,Assumptions!D69) | P19: =CHOOSE(Assumptions!B50,Assumptions!B69,Assumptions!C69,Assumptions!D69) | Q19: =CHOOSE(Assumptions!B50,Assumptions!B69,Assumptions!C69,Assumptions!D69) | R19: =CHOOSE(Assumptions!B50,Assumptions!B69,Assumptions!C69,Assumptions!D69) | S19: =CHOOSE(Assumptions!B50,Assumptions!B69,Assumptions!C69,Assumptions!D69) | T19: =CHOOSE(Assumptions!B50,Assumptions!B69,Assumptions!C69,Assumptions!D69) | U19: =CHOOSE(Assumptions!B50,Assumptions!B69,Assumptions!C69,Assumptions!D69) | V19: =CHOOSE(Assumptions!B50,Assumptions!B69,Assumptions!C69,Assumptions!D69)
A20: (+) D&A ($000s) | B20: =Assumptions!D13 | C20: =C6*C19 | D20: =D6*D19 | E20: =E6*E19 | F20: =F6*F19 | G20: =G6*G19 | H20: =H6*H19 | I20: =I6*I19 | J20: =J6*J19 | ... V20: =V6*V19
A21: CapEx as % Revenue | B21: =(Assumptions!D15+Assumptions!D16)/Assumptions!D6 | C21: =CHOOSE(Assumptions!B50,Assumptions!B70,Assumptions!C70,Assumptions!D70) | D21: =CHOOSE(Assumptions!B50,Assumptions!B70,Assumptions!C70,Assumptions!D70) | E21: =CHOOSE(Assumptions!B50,Assumptions!B70,Assumptions!C70,Assumptions!D70) | F21: =CHOOSE(Assumptions!B50,Assumptions!B70,Assumptions!C70,Assumptions!D70) | G21: =CHOOSE(Assumptions!B50,Assumptions!B70,Assumptions!C70,Assumptions!D70) | H21: =CHOOSE(Assumptions!B50,Assumptions!B70,Assumptions!C70,Assumptions!D70) | I21: =CHOOSE(Assumptions!B50,Assumptions!B70,Assumptions!C70,Assumptions!D70) | J21: =CHOOSE(Assumptions!B50,Assumptions!B70,Assumptions!C70,Assumptions!D70) | K21: =CHOOSE(Assumptions!B50,Assumptions!B70,Assumptions!C70,Assumptions!D70) | L21: =CHOOSE(Assumptions!B50,Assumptions!B70,Assumptions!C70,Assumptions!D70) | M21: =CHOOSE(Assumptions!B50,Assumptions!B70,Assumptions!C70,Assumptions!D70) | N21: =CHOOSE(Assumptions!B50,Assumptions!B70,Assumptions!C70,Assumptions!D70) | O21: =CHOOSE(Assumptions!B50,Assumptions!B70,Assumptions!C70,Assumptions!D70) | P21: =CHOOSE(Assumptions!B50,Assumptions!B70,Assumptions!C70,Assumptions!D70) | Q21: =CHOOSE(Assumptions!B50,Assumptions!B70,Assumptions!C70,Assumptions!D70) | R21: =CHOOSE(Assumptions!B50,Assumptions!B70,Assumptions!C70,Assumptions!D70) | S21: =CHOOSE(Assumptions!B50,Assumptions!B70,Assumptions!C70,Assumptions!D70) | T21: =CHOOSE(Assumptions!B50,Assumptions!B70,Assumptions!C70,Assumptions!D70) | U21: =CHOOSE(Assumptions!B50,Assumptions!B70,Assumptions!C70,Assumptions!D70) | V21: =CHOOSE(Assumptions!B50,Assumptions!B70,Assumptions!C70,Assumptions!D70)
A22: (−) CapEx + Capitalized Software ($000s) | B22: =Assumptions!D15+Assumptions!D16 | C22: =C6*C21 | D22: =D6*D21 | E22: =E6*E21 | F22: =F6*F21 | G22: =G6*G21 | H22: =H6*H21 | I22: =I6*I21 | J22: =J6*J21 | ... V22: =V6*V21
A23: Δ NWC as % Revenue Change | B23: =0 | C23: =CHOOSE(Assumptions!B50,Assumptions!B72,Assumptions!C72,Assumptions!D72) | D23: =CHOOSE(Assumptions!B50,Assumptions!B72,Assumptions!C72,Assumptions!D72) | E23: =CHOOSE(Assumptions!B50,Assumptions!B72,Assumptions!C72,Assumptions!D72) | F23: =CHOOSE(Assumptions!B50,Assumptions!B72,Assumptions!C72,Assumptions!D72) | G23: =CHOOSE(Assumptions!B50,Assumptions!B72,Assumptions!C72,Assumptions!D72) | H23: =CHOOSE(Assumptions!B50,Assumptions!B72,Assumptions!C72,Assumptions!D72) | I23: =CHOOSE(Assumptions!B50,Assumptions!B72,Assumptions!C72,Assumptions!D72) | J23: =CHOOSE(Assumptions!B50,Assumptions!B72,Assumptions!C72,Assumptions!D72) | K23: =CHOOSE(Assumptions!B50,Assumptions!B72,Assumptions!C72,Assumptions!D72) | L23: =CHOOSE(Assumptions!B50,Assumptions!B72,Assumptions!C72,Assumptions!D72) | M23: =CHOOSE(Assumptions!B50,Assumptions!B72,Assumptions!C72,Assumptions!D72) | N23: =CHOOSE(Assumptions!B50,Assumptions!B72,Assumptions!C72,Assumptions!D72) | O23: =CHOOSE(Assumptions!B50,Assumptions!B72,Assumptions!C72,Assumptions!D72) | P23: =CHOOSE(Assumptions!B50,Assumptions!B72,Assumptions!C72,Assumptions!D72) | Q23: =CHOOSE(Assumptions!B50,Assumptions!B72,Assumptions!C72,Assumptions!D72) | R23: =CHOOSE(Assumptions!B50,Assumptions!B72,Assumptions!C72,Assumptions!D72) | S23: =CHOOSE(Assumptions!B50,Assumptions!B72,Assumptions!C72,Assumptions!D72) | T23: =CHOOSE(Assumptions!B50,Assumptions!B72,Assumptions!C72,Assumptions!D72) | U23: =CHOOSE(Assumptions!B50,Assumptions!B72,Assumptions!C72,Assumptions!D72) | V23: =CHOOSE(Assumptions!B50,Assumptions!B72,Assumptions!C72,Assumptions!D72)
A24: (−) Change in NWC ($000s) | B24: =0 | C24: =(C6-B6)*C23 | D24: =(D6-C6)*D23 | E24: =(E6-D6)*E23 | F24: =(F6-E6)*F23 | G24: =(G6-F6)*G23 | H24: =(H6-G6)*H23 | I24: =(I6-H6)*I23 | J24: =(J6-I6)*J23 | ... V24: =(V6-U6)*V23
A25: UNLEVERED FCF ($000s) | B25: =B17+B20-B22-B24 | C25: =C17+C20-C22-C24 | D25: =D17+D20-D22-D24 | E25: =E17+E20-E22-E24 | F25: =F17+F20-F22-F24 | G25: =G17+G20-G22-G24 | H25: =H17+H20-H22-H24 | I25: =I17+I20-I22-I24 | ... V25: =V17+V20-V22-V24
A26: UFCF Margin % | B26: =IF(B6<>0,B25/B6,0) | C26: =IF(C6<>0,C25/C6,0) | D26: =IF(D6<>0,D25/D6,0) | E26: =IF(E6<>0,E25/E6,0) | F26: =IF(F6<>0,F25/F6,0) | G26: =IF(G6<>0,G25/G6,0) | H26: =IF(H6<>0,H25/H6,0) | I26: =IF(I6<>0,I25/I6,0) | ... V26: =IF(V6<>0,V25/V6,0)
A27: D. DISCOUNTING (Mid-Year Convention)
A28: WACC (Active Scenario) | B28: =CHOOSE(Assumptions!B50,Assumptions!B87,Assumptions!C87,Assumptions!D87) | C28: =CHOOSE(Assumptions!B50,Assumptions!B87,Assumptions!C87,Assumptions!D87) | D28: =CHOOSE(Assumptions!B50,Assumptions!B87,Assumptions!C87,Assumptions!D87) | E28: =CHOOSE(Assumptions!B50,Assumptions!B87,Assumptions!C87,Assumptions!D87) | F28: =CHOOSE(Assumptions!B50,Assumptions!B87,Assumptions!C87,Assumptions!D87) | G28: =CHOOSE(Assumptions!B50,Assumptions!B87,Assumptions!C87,Assumptions!D87) | H28: =CHOOSE(Assumptions!B50,Assumptions!B87,Assumptions!C87,Assumptions!D87) | I28: =CHOOSE(Assumptions!B50,Assumptions!B87,Assumptions!C87,Assumptions!D87) | J28: =CHOOSE(Assumptions!B50,Assumptions!B87,Assumptions!C87,Assumptions!D87) | K28: =CHOOSE(Assumptions!B50,Assumptions!B87,Assumptions!C87,Assumptions!D87) | L28: =CHOOSE(Assumptions!B50,Assumptions!B87,Assumptions!C87,Assumptions!D87) | M28: =CHOOSE(Assumptions!B50,Assumptions!B87,Assumptions!C87,Assumptions!D87) | N28: =CHOOSE(Assumptions!B50,Assumptions!B87,Assumptions!C87,Assumptions!D87) | O28: =CHOOSE(Assumptions!B50,Assumptions!B87,Assumptions!C87,Assumptions!D87) | P28: =CHOOSE(Assumptions!B50,Assumptions!B87,Assumptions!C87,Assumptions!D87) | Q28: =CHOOSE(Assumptions!B50,Assumptions!B87,Assumptions!C87,Assumptions!D87) | R28: =CHOOSE(Assumptions!B50,Assumptions!B87,Assumptions!C87,Assumptions!D87) | S28: =CHOOSE(Assumptions!B50,Assumptions!B87,Assumptions!C87,Assumptions!D87) | T28: =CHOOSE(Assumptions!B50,Assumptions!B87,Assumptions!C87,Assumptions!D87) | U28: =CHOOSE(Assumptions!B50,Assumptions!B87,Assumptions!C87,Assumptions!D87) | V28: =CHOOSE(Assumptions!B50,Assumptions!B87,Assumptions!C87,Assumptions!D87)
A29: Discount Period (Mid-Year) | B29: — | C29: =1-0.5 | D29: =2-0.5 | E29: =3-0.5 | F29: =4-0.5 | G29: =5-0.5 | H29: =6-0.5 | I29: =7-0.5 | J29: =8-0.5 | K29: =9-0.5 | L29: =10-0.5 | M29: =11-0.5 | N29: =12-0.5 | O29: =13-0.5 | P29: =14-0.5 | Q29: =15-0.5 | R29: =16-0.5 | S29: =17-0.5 | T29: =18-0.5 | U29: =19-0.5 | V29: =20-0.5
A30: Discount Factor | B30: — | C30: =1/(1+C28)^C29 | D30: =1/(1+D28)^D29 | E30: =1/(1+E28)^E29 | F30: =1/(1+F28)^F29 | G30: =1/(1+G28)^G29 | H30: =1/(1+H28)^H29 | I30: =1/(1+I28)^I29 | J30: =1/(1+J28)^J29 | ... V30: =1/(1+V28)^V29
A31: PV of UFCF ($000s) | B31: — | C31: =C25*C30 | D31: =D25*D30 | E31: =E25*E30 | F31: =F25*F30 | G31: =G25*G30 | H31: =H25*H30 | I31: =I25*I30 | J31: =J25*J30 | ... V31: =V25*V30
A32: Sum of PV (UFCF) — Years 1–20 ($000s) | B32: =SUM(C31:V31)
A33: E. TERMINAL VALUE (Gordon Growth Model — Primary)
A34: Year 20 UFCF ($000s) | B34: =V25
A35: Terminal Growth Rate (Active Scenario) | B35: =CHOOSE(Assumptions!B50,Assumptions!B92,Assumptions!C92,Assumptions!D92)
A36: WACC (Active Scenario) | B36: =CHOOSE(Assumptions!B50,Assumptions!B87,Assumptions!C87,Assumptions!D87)
A37: Terminal Value (undiscounted) ($000s) | B37: =B34*(1+B35)/(B36-B35)
A38: Terminal Value Discount Factor (Year 20) | B38: =1/(1+V28)^20
A39: PV of Terminal Value ($000s) | B39: =B37*B38
A40: Terminal Value as % of Total Enterprise Value | B40: =B39/(B32+B39)
A41: Terminal Value Cross-Check: EV/EBITDA Exit Multiple
A42: Year 20 Revenue ($000s) | B42: =V6
A43: Terminal EBITDA Margin (Active Scenario) | B43: =CHOOSE(Assumptions!B50,Assumptions!B94,Assumptions!C94,Assumptions!D94)
A44: Implied Year 20 EBITDA ($000s) | B44: =B42*B43
A45: Exit EV/EBITDA Multiple (Active Scenario) | B45: =CHOOSE(Assumptions!B50,Assumptions!B93,Assumptions!C93,Assumptions!D93)
A46: Terminal Value — EV/EBITDA Method (undiscounted) ($000s) | B46: =B44*B45
A47: PV of Terminal Value — EV/EBITDA Method ($000s) | B47: =B46*B38
A48: F. ENTERPRISE VALUE → EQUITY VALUE → IMPLIED SHARE PRICE
A49: Enterprise Value — Gordon Growth ($000s) | B49: =B32+B39
A50: Enterprise Value — EV/EBITDA Cross-Check ($000s) | B50: =B32+B47
A51: (−) Net Debt (if Debt > Liquidity) ($000s) | B51: =MAX(0,Assumptions!C32-Assumptions!C27)
A52: (+) Net Cash (if Liquidity > Debt) ($000s) | B52: =MAX(0,Assumptions!C27-Assumptions!C32)
A53: Equity Value — Gordon Growth ($000s) | B53: =B49-B51+B52
A54: Diluted Shares Outstanding | B54: =Assumptions!C34
A55: IMPLIED SHARE PRICE ($) | B55: =IF(B54>0,(B53*1000)/B54,0)
A57: G. SCENARIO SUMMARY (Run each scenario by changing Active Scenario on Assumptions sheet)
A58: Metric | B58: Base Case (Scenario 1) | C58: Bull Case (Scenario 2) | D58: Bear Case (Scenario 3)
A59: FY2026E Revenue ($000s) | B59: =B102 | C59: =C102 | D59: =D102
A60: FY2026E Revenue Growth % | B60: =Assumptions!B40 | C60: =Assumptions!C40 | D60: =Assumptions!D40
A61: FY2030E Revenue ($000s) | B61: =B106 | C61: =C106 | D61: =D106
A62: FY2045E Revenue ($000s) | B62: =B121 | C62: =C121 | D62: =D121
A63: FY2026E Gross Margin % | B63: =Assumptions!B54 | C63: =Assumptions!C54 | D63: =Assumptions!D54
A64: FY2026E EBIT ($000s) | B64: =B102*(Assumptions!B54-Assumptions!B61-Assumptions!B68) | C64: =C102*(Assumptions!C54-Assumptions!C61-Assumptions!C68) | D64: =D102*(Assumptions!D54-Assumptions!D61-Assumptions!D68)
A65: WACC | B65: =Assumptions!B87 | C65: =Assumptions!C87 | D65: =Assumptions!D87
A66: Terminal Growth Rate | B66: =Assumptions!B92 | C66: =Assumptions!C92 | D66: =Assumptions!D92
A67: Sum PV of FCFs ($000s) | B67: =B162 | C67: =C162 | D67: =D162
A68: PV of Terminal Value ($000s) | B68: =B164 | C68: =C164 | D68: =D164
A69: Enterprise Value ($000s) | B69: =B165 | C69: =C165 | D69: =D165
A70: Equity Value ($000s) | B70: =B166 | C70: =C166 | D70: =D166
A71: Implied Share Price ($) | B71: =B167 | C71: =C167 | D71: =D167
A74: H. SENSITIVITY: Implied Share Price ($) — WACC vs Terminal Growth Rate (Base Case)
A75: WACC \ TGR → | B75: 2.0% | C75: 2.5% | D75: 3.0% | E75: 3.5% | F75: 4.0% | G75: 4.5%
A76: 10% | B76: =IF(0.1>0.02,(B122/(1+0.1)^0.5+B123/(1+0.1)^1.5+B124/(1+0.1)^2.5+B125/(1+0.1)^3.5+B126/(1+0.1)^4.5+B127/(1+0.1)^5.5+B128/(1+0.1)^6.5+B129/(1+0.1)^7.5+B130/(1+0.1)^8.5+B131/(1+0.1)^9.5+B132/(1+0.1)^10.5+B133/(1+0.1)^11.5+B134/(1+0.1)^12.5+B135/(1+0.1)^13.5+B136/(1+0.1)^14.5+B137/(1+0.1)^15.5+B138/(1+0.1)^16.5+B139/(1+0.1)^17.5+B140/(1+0.1)^18.5+B141/(1+0.1)^19.5+B141*(1+0.02)/(0.1-0.02)/(1+0.1)^20-MAX(0,Assumptions!C32-Assumptions!C27)+MAX(0,Assumptions!C27-Assumptions!C32))*1000/Assumptions!C34,"-") | C76: =IF(0.1>0.025,(B122/(1+0.1)^0.5+B123/(1+0.1)^1.5+B124/(1+0.1)^2.5+B125/(1+0.1)^3.5+B126/(1+0.1)^4.5+B127/(1+0.1)^5.5+B128/(1+0.1)^6.5+B129/(1+0.1)^7.5+B130/(1+0.1)^8.5+B131/(1+0.1)^9.5+B132/(1+0.1)^10.5+B133/(1+0.1)^11.5+B134/(1+0.1)^12.5+B135/(1+0.1)^13.5+B136/(1+0.1)^14.5+B137/(1+0.1)^15.5+B138/(1+0.1)^16.5+B139/(1+0.1)^17.5+B140/(1+0.1)^18.5+B141/(1+0.1)^19.5+B141*(1+0.025)/(0.1-0.025)/(1+0.1)^20-MAX(0,Assumptions!C32-Assumptions!C27)+MAX(0,Assumptions!C27-Assumptions!C32))*1000/Assumptions!C34,"-") | D76: =IF(0.1>0.03,(B122/(1+0.1)^0.5+B123/(1+0.1)^1.5+B124/(1+0.1)^2.5+B125/(1+0.1)^3.5+B126/(1+0.1)^4.5+B127/(1+0.1)^5.5+B128/(1+0.1)^6.5+B129/(1+0.1)^7.5+B130/(1+0.1)^8.5+B131/(1+0.1)^9.5+B132/(1+0.1)^10.5+B133/(1+0.1)^11.5+B134/(1+0.1)^12.5+B135/(1+0.1)^13.5+B136/(1+0.1)^14.5+B137/(1+0.1)^15.5+B138/(1+0.1)^16.5+B139/(1+0.1)^17.5+B140/(1+0.1)^18.5+B141/(1+0.1)^19.5+B141*(1+0.03)/(0.1-0.03)/(1+0.1)^20-MAX(0,Assumptions!C32-Assumptions!C27)+MAX(0,Assumptions!C27-Assumptions!C32))*1000/Assumptions!C34,"-") | E76: =IF(0.1>0.035,(B122/(1+0.1)^0.5+B123/(1+0.1)^1.5+B124/(1+0.1)^2.5+B125/(1+0.1)^3.5+B126/(1+0.1)^4.5+B127/(1+0.1)^5.5+B128/(1+0.1)^6.5+B129/(1+0.1)^7.5+B130/(1+0.1)^8.5+B131/(1+0.1)^9.5+B132/(1+0.1)^10.5+B133/(1+0.1)^11.5+B134/(1+0.1)^12.5+B135/(1+0.1)^13.5+B136/(1+0.1)^14.5+B137/(1+0.1)^15.5+B138/(1+0.1)^16.5+B139/(1+0.1)^17.5+B140/(1+0.1)^18.5+B141/(1+0.1)^19.5+B141*(1+0.035)/(0.1-0.035)/(1+0.1)^20-MAX(0,Assumptions!C32-Assumptions!C27)+MAX(0,Assumptions!C27-Assumptions!C32))*1000/Assumptions!C34,"-") | F76: =IF(0.1>0.04,(B122/(1+0.1)^0.5+B123/(1+0.1)^1.5+B124/(1+0.1)^2.5+B125/(1+0.1)^3.5+B126/(1+0.1)^4.5+B127/(1+0.1)^5.5+B128/(1+0.1)^6.5+B129/(1+0.1)^7.5+B130/(1+0.1)^8.5+B131/(1+0.1)^9.5+B132/(1+0.1)^10.5+B133/(1+0.1)^11.5+B134/(1+0.1)^12.5+B135/(1+0.1)^13.5+B136/(1+0.1)^14.5+B137/(1+0.1)^15.5+B138/(1+0.1)^16.5+B139/(1+0.1)^17.5+B140/(1+0.1)^18.5+B141/(1+0.1)^19.5+B141*(1+0.04)/(0.1-0.04)/(1+0.1)^20-MAX(0,Assumptions!C32-Assumptions!C27)+MAX(0,Assumptions!C27-Assumptions!C32))*1000/Assumptions!C34,"-") | G76: =IF(0.1>0.045,(B122/(1+0.1)^0.5+B123/(1+0.1)^1.5+B124/(1+0.1)^2.5+B125/(1+0.1)^3.5+B126/(1+0.1)^4.5+B127/(1+0.1)^5.5+B128/(1+0.1)^6.5+B129/(1+0.1)^7.5+B130/(1+0.1)^8.5+B131/(1+0.1)^9.5+B132/(1+0.1)^10.5+B133/(1+0.1)^11.5+B134/(1+0.1)^12.5+B135/(1+0.1)^13.5+B136/(1+0.1)^14.5+B137/(1+0.1)^15.5+B138/(1+0.1)^16.5+B139/(1+0.1)^17.5+B140/(1+0.1)^18.5+B141/(1+0.1)^19.5+B141*(1+0.045)/(0.1-0.045)/(1+0.1)^20-MAX(0,Assumptions!C32-Assumptions!C27)+MAX(0,Assumptions!C27-Assumptions!C32))*1000/Assumptions!C34,"-")
A77: 12% | B77: =IF(0.12>0.02,(B122/(1+0.12)^0.5+B123/(1+0.12)^1.5+B124/(1+0.12)^2.5+B125/(1+0.12)^3.5+B126/(1+0.12)^4.5+B127/(1+0.12)^5.5+B128/(1+0.12)^6.5+B129/(1+0.12)^7.5+B130/(1+0.12)^8.5+B131/(1+0.12)^9.5+B132/(1+0.12)^10.5+B133/(1+0.12)^11.5+B134/(1+0.12)^12.5+B135/(1+0.12)^13.5+B136/(1+0.12)^14.5+B137/(1+0.12)^15.5+B138/(1+0.12)^16.5+B139/(1+0.12)^17.5+B140/(1+0.12)^18.5+B141/(1+0.12)^19.5+B141*(1+0.02)/(0.12-0.02)/(1+0.12)^20-MAX(0,Assumptions!C32-Assumptions!C27)+MAX(0,Assumptions!C27-Assumptions!C32))*1000/Assumptions!C34,"-") | C77: =IF(0.12>0.025,(B122/(1+0.12)^0.5+B123/(1+0.12)^1.5+B124/(1+0.12)^2.5+B125/(1+0.12)^3.5+B126/(1+0.12)^4.5+B127/(1+0.12)^5.5+B128/(1+0.12)^6.5+B129/(1+0.12)^7.5+B130/(1+0.12)^8.5+B131/(1+0.12)^9.5+B132/(1+0.12)^10.5+B133/(1+0.12)^11.5+B134/(1+0.12)^12.5+B135/(1+0.12)^13.5+B136/(1+0.12)^14.5+B137/(1+0.12)^15.5+B138/(1+0.12)^16.5+B139/(1+0.12)^17.5+B140/(1+0.12)^18.5+B141/(1+0.12)^19.5+B141*(1+0.025)/(0.12-0.025)/(1+0.12)^20-MAX(0,Assumptions!C32-Assumptions!C27)+MAX(0,Assumptions!C27-Assumptions!C32))*1000/Assumptions!C34,"-") | D77: =IF(0.12>0.03,(B122/(1+0.12)^0.5+B123/(1+0.12)^1.5+B124/(1+0.12)^2.5+B125/(1+0.12)^3.5+B126/(1+0.12)^4.5+B127/(1+0.12)^5.5+B128/(1+0.12)^6.5+B129/(1+0.12)^7.5+B130/(1+0.12)^8.5+B131/(1+0.12)^9.5+B132/(1+0.12)^10.5+B133/(1+0.12)^11.5+B134/(1+0.12)^12.5+B135/(1+0.12)^13.5+B136/(1+0.12)^14.5+B137/(1+0.12)^15.5+B138/(1+0.12)^16.5+B139/(1+0.12)^17.5+B140/(1+0.12)^18.5+B141/(1+0.12)^19.5+B141*(1+0.03)/(0.12-0.03)/(1+0.12)^20-MAX(0,Assumptions!C32-Assumptions!C27)+MAX(0,Assumptions!C27-Assumptions!C32))*1000/Assumptions!C34,"-") | E77: =IF(0.12>0.035,(B122/(1+0.12)^0.5+B123/(1+0.12)^1.5+B124/(1+0.12)^2.5+B125/(1+0.12)^3.5+B126/(1+0.12)^4.5+B127/(1+0.12)^5.5+B128/(1+0.12)^6.5+B129/(1+0.12)^7.5+B130/(1+0.12)^8.5+B131/(1+0.12)^9.5+B132/(1+0.12)^10.5+B133/(1+0.12)^11.5+B134/(1+0.12)^12.5+B135/(1+0.12)^13.5+B136/(1+0.12)^14.5+B137/(1+0.12)^15.5+B138/(1+0.12)^16.5+B139/(1+0.12)^17.5+B140/(1+0.12)^18.5+B141/(1+0.12)^19.5+B141*(1+0.035)/(0.12-0.035)/(1+0.12)^20-MAX(0,Assumptions!C32-Assumptions!C27)+MAX(0,Assumptions!C27-Assumptions!C32))*1000/Assumptions!C34,"-") | F77: =IF(0.12>0.04,(B122/(1+0.12)^0.5+B123/(1+0.12)^1.5+B124/(1+0.12)^2.5+B125/(1+0.12)^3.5+B126/(1+0.12)^4.5+B127/(1+0.12)^5.5+B128/(1+0.12)^6.5+B129/(1+0.12)^7.5+B130/(1+0.12)^8.5+B131/(1+0.12)^9.5+B132/(1+0.12)^10.5+B133/(1+0.12)^11.5+B134/(1+0.12)^12.5+B135/(1+0.12)^13.5+B136/(1+0.12)^14.5+B137/(1+0.12)^15.5+B138/(1+0.12)^16.5+B139/(1+0.12)^17.5+B140/(1+0.12)^18.5+B141/(1+0.12)^19.5+B141*(1+0.04)/(0.12-0.04)/(1+0.12)^20-MAX(0,Assumptions!C32-Assumptions!C27)+MAX(0,Assumptions!C27-Assumptions!C32))*1000/Assumptions!C34,"-") | G77: =IF(0.12>0.045,(B122/(1+0.12)^0.5+B123/(1+0.12)^1.5+B124/(1+0.12)^2.5+B125/(1+0.12)^3.5+B126/(1+0.12)^4.5+B127/(1+0.12)^5.5+B128/(1+0.12)^6.5+B129/(1+0.12)^7.5+B130/(1+0.12)^8.5+B131/(1+0.12)^9.5+B132/(1+0.12)^10.5+B133/(1+0.12)^11.5+B134/(1+0.12)^12.5+B135/(1+0.12)^13.5+B136/(1+0.12)^14.5+B137/(1+0.12)^15.5+B138/(1+0.12)^16.5+B139/(1+0.12)^17.5+B140/(1+0.12)^18.5+B141/(1+0.12)^19.5+B141*(1+0.045)/(0.12-0.045)/(1+0.12)^20-MAX(0,Assumptions!C32-Assumptions!C27)+MAX(0,Assumptions!C27-Assumptions!C32))*1000/Assumptions!C34,"-")
A78: 14% | B78: =IF(0.14>0.02,(B122/(1+0.14)^0.5+B123/(1+0.14)^1.5+B124/(1+0.14)^2.5+B125/(1+0.14)^3.5+B126/(1+0.14)^4.5+B127/(1+0.14)^5.5+B128/(1+0.14)^6.5+B129/(1+0.14)^7.5+B130/(1+0.14)^8.5+B131/(1+0.14)^9.5+B132/(1+0.14)^10.5+B133/(1+0.14)^11.5+B134/(1+0.14)^12.5+B135/(1+0.14)^13.5+B136/(1+0.14)^14.5+B137/(1+0.14)^15.5+B138/(1+0.14)^16.5+B139/(1+0.14)^17.5+B140/(1+0.14)^18.5+B141/(1+0.14)^19.5+B141*(1+0.02)/(0.14-0.02)/(1+0.14)^20-MAX(0,Assumptions!C32-Assumptions!C27)+MAX(0,Assumptions!C27-Assumptions!C32))*1000/Assumptions!C34,"-") | C78: =IF(0.14>0.025,(B122/(1+0.14)^0.5+B123/(1+0.14)^1.5+B124/(1+0.14)^2.5+B125/(1+0.14)^3.5+B126/(1+0.14)^4.5+B127/(1+0.14)^5.5+B128/(1+0.14)^6.5+B129/(1+0.14)^7.5+B130/(1+0.14)^8.5+B131/(1+0.14)^9.5+B132/(1+0.14)^10.5+B133/(1+0.14)^11.5+B134/(1+0.14)^12.5+B135/(1+0.14)^13.5+B136/(1+0.14)^14.5+B137/(1+0.14)^15.5+B138/(1+0.14)^16.5+B139/(1+0.14)^17.5+B140/(1+0.14)^18.5+B141/(1+0.14)^19.5+B141*(1+0.025)/(0.14-0.025)/(1+0.14)^20-MAX(0,Assumptions!C32-Assumptions!C27)+MAX(0,Assumptions!C27-Assumptions!C32))*1000/Assumptions!C34,"-") | D78: =IF(0.14>0.03,(B122/(1+0.14)^0.5+B123/(1+0.14)^1.5+B124/(1+0.14)^2.5+B125/(1+0.14)^3.5+B126/(1+0.14)^4.5+B127/(1+0.14)^5.5+B128/(1+0.14)^6.5+B129/(1+0.14)^7.5+B130/(1+0.14)^8.5+B131/(1+0.14)^9.5+B132/(1+0.14)^10.5+B133/(1+0.14)^11.5+B134/(1+0.14)^12.5+B135/(1+0.14)^13.5+B136/(1+0.14)^14.5+B137/(1+0.14)^15.5+B138/(1+0.14)^16.5+B139/(1+0.14)^17.5+B140/(1+0.14)^18.5+B141/(1+0.14)^19.5+B141*(1+0.03)/(0.14-0.03)/(1+0.14)^20-MAX(0,Assumptions!C32-Assumptions!C27)+MAX(0,Assumptions!C27-Assumptions!C32))*1000/Assumptions!C34,"-") | E78: =IF(0.14>0.035,(B122/(1+0.14)^0.5+B123/(1+0.14)^1.5+B124/(1+0.14)^2.5+B125/(1+0.14)^3.5+B126/(1+0.14)^4.5+B127/(1+0.14)^5.5+B128/(1+0.14)^6.5+B129/(1+0.14)^7.5+B130/(1+0.14)^8.5+B131/(1+0.14)^9.5+B132/(1+0.14)^10.5+B133/(1+0.14)^11.5+B134/(1+0.14)^12.5+B135/(1+0.14)^13.5+B136/(1+0.14)^14.5+B137/(1+0.14)^15.5+B138/(1+0.14)^16.5+B139/(1+0.14)^17.5+B140/(1+0.14)^18.5+B141/(1+0.14)^19.5+B141*(1+0.035)/(0.14-0.035)/(1+0.14)^20-MAX(0,Assumptions!C32-Assumptions!C27)+MAX(0,Assumptions!C27-Assumptions!C32))*1000/Assumptions!C34,"-") | F78: =IF(0.14>0.04,(B122/(1+0.14)^0.5+B123/(1+0.14)^1.5+B124/(1+0.14)^2.5+B125/(1+0.14)^3.5+B126/(1+0.14)^4.5+B127/(1+0.14)^5.5+B128/(1+0.14)^6.5+B129/(1+0.14)^7.5+B130/(1+0.14)^8.5+B131/(1+0.14)^9.5+B132/(1+0.14)^10.5+B133/(1+0.14)^11.5+B134/(1+0.14)^12.5+B135/(1+0.14)^13.5+B136/(1+0.14)^14.5+B137/(1+0.14)^15.5+B138/(1+0.14)^16.5+B139/(1+0.14)^17.5+B140/(1+0.14)^18.5+B141/(1+0.14)^19.5+B141*(1+0.04)/(0.14-0.04)/(1+0.14)^20-MAX(0,Assumptions!C32-Assumptions!C27)+MAX(0,Assumptions!C27-Assumptions!C32))*1000/Assumptions!C34,"-") | G78: =IF(0.14>0.045,(B122/(1+0.14)^0.5+B123/(1+0.14)^1.5+B124/(1+0.14)^2.5+B125/(1+0.14)^3.5+B126/(1+0.14)^4.5+B127/(1+0.14)^5.5+B128/(1+0.14)^6.5+B129/(1+0.14)^7.5+B130/(1+0.14)^8.5+B131/(1+0.14)^9.5+B132/(1+0.14)^10.5+B133/(1+0.14)^11.5+B134/(1+0.14)^12.5+B135/(1+0.14)^13.5+B136/(1+0.14)^14.5+B137/(1+0.14)^15.5+B138/(1+0.14)^16.5+B139/(1+0.14)^17.5+B140/(1+0.14)^18.5+B141/(1+0.14)^19.5+B141*(1+0.045)/(0.14-0.045)/(1+0.14)^20-MAX(0,Assumptions!C32-Assumptions!C27)+MAX(0,Assumptions!C27-Assumptions!C32))*1000/Assumptions!C34,"-")
A79: 16% | B79: =IF(0.16>0.02,(B122/(1+0.16)^0.5+B123/(1+0.16)^1.5+B124/(1+0.16)^2.5+B125/(1+0.16)^3.5+B126/(1+0.16)^4.5+B127/(1+0.16)^5.5+B128/(1+0.16)^6.5+B129/(1+0.16)^7.5+B130/(1+0.16)^8.5+B131/(1+0.16)^9.5+B132/(1+0.16)^10.5+B133/(1+0.16)^11.5+B134/(1+0.16)^12.5+B135/(1+0.16)^13.5+B136/(1+0.16)^14.5+B137/(1+0.16)^15.5+B138/(1+0.16)^16.5+B139/(1+0.16)^17.5+B140/(1+0.16)^18.5+B141/(1+0.16)^19.5+B141*(1+0.02)/(0.16-0.02)/(1+0.16)^20-MAX(0,Assumptions!C32-Assumptions!C27)+MAX(0,Assumptions!C27-Assumptions!C32))*1000/Assumptions!C34,"-") | C79: =IF(0.16>0.025,(B122/(1+0.16)^0.5+B123/(1+0.16)^1.5+B124/(1+0.16)^2.5+B125/(1+0.16)^3.5+B126/(1+0.16)^4.5+B127/(1+0.16)^5.5+B128/(1+0.16)^6.5+B129/(1+0.16)^7.5+B130/(1+0.16)^8.5+B131/(1+0.16)^9.5+B132/(1+0.16)^10.5+B133/(1+0.16)^11.5+B134/(1+0.16)^12.5+B135/(1+0.16)^13.5+B136/(1+0.16)^14.5+B137/(1+0.16)^15.5+B138/(1+0.16)^16.5+B139/(1+0.16)^17.5+B140/(1+0.16)^18.5+B141/(1+0.16)^19.5+B141*(1+0.025)/(0.16-0.025)/(1+0.16)^20-MAX(0,Assumptions!C32-Assumptions!C27)+MAX(0,Assumptions!C27-Assumptions!C32))*1000/Assumptions!C34,"-") | D79: =IF(0.16>0.03,(B122/(1+0.16)^0.5+B123/(1+0.16)^1.5+B124/(1+0.16)^2.5+B125/(1+0.16)^3.5+B126/(1+0.16)^4.5+B127/(1+0.16)^5.5+B128/(1+0.16)^6.5+B129/(1+0.16)^7.5+B130/(1+0.16)^8.5+B131/(1+0.16)^9.5+B132/(1+0.16)^10.5+B133/(1+0.16)^11.5+B134/(1+0.16)^12.5+B135/(1+0.16)^13.5+B136/(1+0.16)^14.5+B137/(1+0.16)^15.5+B138/(1+0.16)^16.5+B139/(1+0.16)^17.5+B140/(1+0.16)^18.5+B141/(1+0.16)^19.5+B141*(1+0.03)/(0.16-0.03)/(1+0.16)^20-MAX(0,Assumptions!C32-Assumptions!C27)+MAX(0,Assumptions!C27-Assumptions!C32))*1000/Assumptions!C34,"-") | E79: =IF(0.16>0.035,(B122/(1+0.16)^0.5+B123/(1+0.16)^1.5+B124/(1+0.16)^2.5+B125/(1+0.16)^3.5+B126/(1+0.16)^4.5+B127/(1+0.16)^5.5+B128/(1+0.16)^6.5+B129/(1+0.16)^7.5+B130/(1+0.16)^8.5+B131/(1+0.16)^9.5+B132/(1+0.16)^10.5+B133/(1+0.16)^11.5+B134/(1+0.16)^12.5+B135/(1+0.16)^13.5+B136/(1+0.16)^14.5+B137/(1+0.16)^15.5+B138/(1+0.16)^16.5+B139/(1+0.16)^17.5+B140/(1+0.16)^18.5+B141/(1+0.16)^19.5+B141*(1+0.035)/(0.16-0.035)/(1+0.16)^20-MAX(0,Assumptions!C32-Assumptions!C27)+MAX(0,Assumptions!C27-Assumptions!C32))*1000/Assumptions!C34,"-") | F79: =IF(0.16>0.04,(B122/(1+0.16)^0.5+B123/(1+0.16)^1.5+B124/(1+0.16)^2.5+B125/(1+0.16)^3.5+B126/(1+0.16)^4.5+B127/(1+0.16)^5.5+B128/(1+0.16)^6.5+B129/(1+0.16)^7.5+B130/(1+0.16)^8.5+B131/(1+0.16)^9.5+B132/(1+0.16)^10.5+B133/(1+0.16)^11.5+B134/(1+0.16)^12.5+B135/(1+0.16)^13.5+B136/(1+0.16)^14.5+B137/(1+0.16)^15.5+B138/(1+0.16)^16.5+B139/(1+0.16)^17.5+B140/(1+0.16)^18.5+B141/(1+0.16)^19.5+B141*(1+0.04)/(0.16-0.04)/(1+0.16)^20-MAX(0,Assumptions!C32-Assumptions!C27)+MAX(0,Assumptions!C27-Assumptions!C32))*1000/Assumptions!C34,"-") | G79: =IF(0.16>0.045,(B122/(1+0.16)^0.5+B123/(1+0.16)^1.5+B124/(1+0.16)^2.5+B125/(1+0.16)^3.5+B126/(1+0.16)^4.5+B127/(1+0.16)^5.5+B128/(1+0.16)^6.5+B129/(1+0.16)^7.5+B130/(1+0.16)^8.5+B131/(1+0.16)^9.5+B132/(1+0.16)^10.5+B133/(1+0.16)^11.5+B134/(1+0.16)^12.5+B135/(1+0.16)^13.5+B136/(1+0.16)^14.5+B137/(1+0.16)^15.5+B138/(1+0.16)^16.5+B139/(1+0.16)^17.5+B140/(1+0.16)^18.5+B141/(1+0.16)^19.5+B141*(1+0.045)/(0.16-0.045)/(1+0.16)^20-MAX(0,Assumptions!C32-Assumptions!C27)+MAX(0,Assumptions!C27-Assumptions!C32))*1000/Assumptions!C34,"-")
A80: 18% | B80: =IF(0.18>0.02,(B122/(1+0.18)^0.5+B123/(1+0.18)^1.5+B124/(1+0.18)^2.5+B125/(1+0.18)^3.5+B126/(1+0.18)^4.5+B127/(1+0.18)^5.5+B128/(1+0.18)^6.5+B129/(1+0.18)^7.5+B130/(1+0.18)^8.5+B131/(1+0.18)^9.5+B132/(1+0.18)^10.5+B133/(1+0.18)^11.5+B134/(1+0.18)^12.5+B135/(1+0.18)^13.5+B136/(1+0.18)^14.5+B137/(1+0.18)^15.5+B138/(1+0.18)^16.5+B139/(1+0.18)^17.5+B140/(1+0.18)^18.5+B141/(1+0.18)^19.5+B141*(1+0.02)/(0.18-0.02)/(1+0.18)^20-MAX(0,Assumptions!C32-Assumptions!C27)+MAX(0,Assumptions!C27-Assumptions!C32))*1000/Assumptions!C34,"-") | C80: =IF(0.18>0.025,(B122/(1+0.18)^0.5+B123/(1+0.18)^1.5+B124/(1+0.18)^2.5+B125/(1+0.18)^3.5+B126/(1+0.18)^4.5+B127/(1+0.18)^5.5+B128/(1+0.18)^6.5+B129/(1+0.18)^7.5+B130/(1+0.18)^8.5+B131/(1+0.18)^9.5+B132/(1+0.18)^10.5+B133/(1+0.18)^11.5+B134/(1+0.18)^12.5+B135/(1+0.18)^13.5+B136/(1+0.18)^14.5+B137/(1+0.18)^15.5+B138/(1+0.18)^16.5+B139/(1+0.18)^17.5+B140/(1+0.18)^18.5+B141/(1+0.18)^19.5+B141*(1+0.025)/(0.18-0.025)/(1+0.18)^20-MAX(0,Assumptions!C32-Assumptions!C27)+MAX(0,Assumptions!C27-Assumptions!C32))*1000/Assumptions!C34,"-") | D80: =IF(0.18>0.03,(B122/(1+0.18)^0.5+B123/(1+0.18)^1.5+B124/(1+0.18)^2.5+B125/(1+0.18)^3.5+B126/(1+0.18)^4.5+B127/(1+0.18)^5.5+B128/(1+0.18)^6.5+B129/(1+0.18)^7.5+B130/(1+0.18)^8.5+B131/(1+0.18)^9.5+B132/(1+0.18)^10.5+B133/(1+0.18)^11.5+B134/(1+0.18)^12.5+B135/(1+0.18)^13.5+B136/(1+0.18)^14.5+B137/(1+0.18)^15.5+B138/(1+0.18)^16.5+B139/(1+0.18)^17.5+B140/(1+0.18)^18.5+B141/(1+0.18)^19.5+B141*(1+0.03)/(0.18-0.03)/(1+0.18)^20-MAX(0,Assumptions!C32-Assumptions!C27)+MAX(0,Assumptions!C27-Assumptions!C32))*1000/Assumptions!C34,"-") | E80: =IF(0.18>0.035,(B122/(1+0.18)^0.5+B123/(1+0.18)^1.5+B124/(1+0.18)^2.5+B125/(1+0.18)^3.5+B126/(1+0.18)^4.5+B127/(1+0.18)^5.5+B128/(1+0.18)^6.5+B129/(1+0.18)^7.5+B130/(1+0.18)^8.5+B131/(1+0.18)^9.5+B132/(1+0.18)^10.5+B133/(1+0.18)^11.5+B134/(1+0.18)^12.5+B135/(1+0.18)^13.5+B136/(1+0.18)^14.5+B137/(1+0.18)^15.5+B138/(1+0.18)^16.5+B139/(1+0.18)^17.5+B140/(1+0.18)^18.5+B141/(1+0.18)^19.5+B141*(1+0.035)/(0.18-0.035)/(1+0.18)^20-MAX(0,Assumptions!C32-Assumptions!C27)+MAX(0,Assumptions!C27-Assumptions!C32))*1000/Assumptions!C34,"-") | F80: =IF(0.18>0.04,(B122/(1+0.18)^0.5+B123/(1+0.18)^1.5+B124/(1+0.18)^2.5+B125/(1+0.18)^3.5+B126/(1+0.18)^4.5+B127/(1+0.18)^5.5+B128/(1+0.18)^6.5+B129/(1+0.18)^7.5+B130/(1+0.18)^8.5+B131/(1+0.18)^9.5+B132/(1+0.18)^10.5+B133/(1+0.18)^11.5+B134/(1+0.18)^12.5+B135/(1+0.18)^13.5+B136/(1+0.18)^14.5+B137/(1+0.18)^15.5+B138/(1+0.18)^16.5+B139/(1+0.18)^17.5+B140/(1+0.18)^18.5+B141/(1+0.18)^19.5+B141*(1+0.04)/(0.18-0.04)/(1+0.18)^20-MAX(0,Assumptions!C32-Assumptions!C27)+MAX(0,Assumptions!C27-Assumptions!C32))*1000/Assumptions!C34,"-") | G80: =IF(0.18>0.045,(B122/(1+0.18)^0.5+B123/(1+0.18)^1.5+B124/(1+0.18)^2.5+B125/(1+0.18)^3.5+B126/(1+0.18)^4.5+B127/(1+0.18)^5.5+B128/(1+0.18)^6.5+B129/(1+0.18)^7.5+B130/(1+0.18)^8.5+B131/(1+0.18)^9.5+B132/(1+0.18)^10.5+B133/(1+0.18)^11.5+B134/(1+0.18)^12.5+B135/(1+0.18)^13.5+B136/(1+0.18)^14.5+B137/(1+0.18)^15.5+B138/(1+0.18)^16.5+B139/(1+0.18)^17.5+B140/(1+0.18)^18.5+B141/(1+0.18)^19.5+B141*(1+0.045)/(0.18-0.045)/(1+0.18)^20-MAX(0,Assumptions!C32-Assumptions!C27)+MAX(0,Assumptions!C27-Assumptions!C32))*1000/Assumptions!C34,"-")
A81: 20% | B81: =IF(0.2>0.02,(B122/(1+0.2)^0.5+B123/(1+0.2)^1.5+B124/(1+0.2)^2.5+B125/(1+0.2)^3.5+B126/(1+0.2)^4.5+B127/(1+0.2)^5.5+B128/(1+0.2)^6.5+B129/(1+0.2)^7.5+B130/(1+0.2)^8.5+B131/(1+0.2)^9.5+B132/(1+0.2)^10.5+B133/(1+0.2)^11.5+B134/(1+0.2)^12.5+B135/(1+0.2)^13.5+B136/(1+0.2)^14.5+B137/(1+0.2)^15.5+B138/(1+0.2)^16.5+B139/(1+0.2)^17.5+B140/(1+0.2)^18.5+B141/(1+0.2)^19.5+B141*(1+0.02)/(0.2-0.02)/(1+0.2)^20-MAX(0,Assumptions!C32-Assumptions!C27)+MAX(0,Assumptions!C27-Assumptions!C32))*1000/Assumptions!C34,"-") | C81: =IF(0.2>0.025,(B122/(1+0.2)^0.5+B123/(1+0.2)^1.5+B124/(1+0.2)^2.5+B125/(1+0.2)^3.5+B126/(1+0.2)^4.5+B127/(1+0.2)^5.5+B128/(1+0.2)^6.5+B129/(1+0.2)^7.5+B130/(1+0.2)^8.5+B131/(1+0.2)^9.5+B132/(1+0.2)^10.5+B133/(1+0.2)^11.5+B134/(1+0.2)^12.5+B135/(1+0.2)^13.5+B136/(1+0.2)^14.5+B137/(1+0.2)^15.5+B138/(1+0.2)^16.5+B139/(1+0.2)^17.5+B140/(1+0.2)^18.5+B141/(1+0.2)^19.5+B141*(1+0.025)/(0.2-0.025)/(1+0.2)^20-MAX(0,Assumptions!C32-Assumptions!C27)+MAX(0,Assumptions!C27-Assumptions!C32))*1000/Assumptions!C34,"-") | D81: =IF(0.2>0.03,(B122/(1+0.2)^0.5+B123/(1+0.2)^1.5+B124/(1+0.2)^2.5+B125/(1+0.2)^3.5+B126/(1+0.2)^4.5+B127/(1+0.2)^5.5+B128/(1+0.2)^6.5+B129/(1+0.2)^7.5+B130/(1+0.2)^8.5+B131/(1+0.2)^9.5+B132/(1+0.2)^10.5+B133/(1+0.2)^11.5+B134/(1+0.2)^12.5+B135/(1+0.2)^13.5+B136/(1+0.2)^14.5+B137/(1+0.2)^15.5+B138/(1+0.2)^16.5+B139/(1+0.2)^17.5+B140/(1+0.2)^18.5+B141/(1+0.2)^19.5+B141*(1+0.03)/(0.2-0.03)/(1+0.2)^20-MAX(0,Assumptions!C32-Assumptions!C27)+MAX(0,Assumptions!C27-Assumptions!C32))*1000/Assumptions!C34,"-") | E81: =IF(0.2>0.035,(B122/(1+0.2)^0.5+B123/(1+0.2)^1.5+B124/(1+0.2)^2.5+B125/(1+0.2)^3.5+B126/(1+0.2)^4.5+B127/(1+0.2)^5.5+B128/(1+0.2)^6.5+B129/(1+0.2)^7.5+B130/(1+0.2)^8.5+B131/(1+0.2)^9.5+B132/(1+0.2)^10.5+B133/(1+0.2)^11.5+B134/(1+0.2)^12.5+B135/(1+0.2)^13.5+B136/(1+0.2)^14.5+B137/(1+0.2)^15.5+B138/(1+0.2)^16.5+B139/(1+0.2)^17.5+B140/(1+0.2)^18.5+B141/(1+0.2)^19.5+B141*(1+0.035)/(0.2-0.035)/(1+0.2)^20-MAX(0,Assumptions!C32-Assumptions!C27)+MAX(0,Assumptions!C27-Assumptions!C32))*1000/Assumptions!C34,"-") | F81: =IF(0.2>0.04,(B122/(1+0.2)^0.5+B123/(1+0.2)^1.5+B124/(1+0.2)^2.5+B125/(1+0.2)^3.5+B126/(1+0.2)^4.5+B127/(1+0.2)^5.5+B128/(1+0.2)^6.5+B129/(1+0.2)^7.5+B130/(1+0.2)^8.5+B131/(1+0.2)^9.5+B132/(1+0.2)^10.5+B133/(1+0.2)^11.5+B134/(1+0.2)^12.5+B135/(1+0.2)^13.5+B136/(1+0.2)^14.5+B137/(1+0.2)^15.5+B138/(1+0.2)^16.5+B139/(1+0.2)^17.5+B140/(1+0.2)^18.5+B141/(1+0.2)^19.5+B141*(1+0.04)/(0.2-0.04)/(1+0.2)^20-MAX(0,Assumptions!C32-Assumptions!C27)+MAX(0,Assumptions!C27-Assumptions!C32))*1000/Assumptions!C34,"-") | G81: =IF(0.2>0.045,(B122/(1+0.2)^0.5+B123/(1+0.2)^1.5+B124/(1+0.2)^2.5+B125/(1+0.2)^3.5+B126/(1+0.2)^4.5+B127/(1+0.2)^5.5+B128/(1+0.2)^6.5+B129/(1+0.2)^7.5+B130/(1+0.2)^8.5+B131/(1+0.2)^9.5+B132/(1+0.2)^10.5+B133/(1+0.2)^11.5+B134/(1+0.2)^12.5+B135/(1+0.2)^13.5+B136/(1+0.2)^14.5+B137/(1+0.2)^15.5+B138/(1+0.2)^16.5+B139/(1+0.2)^17.5+B140/(1+0.2)^18.5+B141/(1+0.2)^19.5+B141*(1+0.045)/(0.2-0.045)/(1+0.2)^20-MAX(0,Assumptions!C32-Assumptions!C27)+MAX(0,Assumptions!C27-Assumptions!C32))*1000/Assumptions!C34,"-")
A100: ── SCENARIO ENGINE (helper rows – do not edit) ──
A101: Metric | B101: Base | C101: Bull | D101: Bear
A102: Rev 2026 | B102: =Assumptions!D6*(1+Assumptions!B40) | C102: =Assumptions!D6*(1+Assumptions!C40) | D102: =Assumptions!D6*(1+Assumptions!D40)
A103: Rev 2027 | B103: =B102*(1+Assumptions!B41) | C103: =C102*(1+Assumptions!C41) | D103: =D102*(1+Assumptions!D41)
A104: Rev 2028 | B104: =B103*(1+Assumptions!B42) | C104: =C103*(1+Assumptions!C42) | D104: =D103*(1+Assumptions!D42)
A105: Rev 2029 | B105: =B104*(1+Assumptions!B43) | C105: =C104*(1+Assumptions!C43) | D105: =D104*(1+Assumptions!D43)
A106: Rev 2030 | B106: =B105*(1+Assumptions!B44) | C106: =C105*(1+Assumptions!C44) | D106: =D105*(1+Assumptions!D44)
A107: Rev 2031 | B107: =B106*(1+Assumptions!B45) | C107: =C106*(1+Assumptions!C45) | D107: =D106*(1+Assumptions!D45)
A108: Rev 2032 | B108: =B107*(1+Assumptions!B45) | C108: =C107*(1+Assumptions!C45) | D108: =D107*(1+Assumptions!D45)
A109: Rev 2033 | B109: =B108*(1+Assumptions!B45) | C109: =C108*(1+Assumptions!C45) | D109: =D108*(1+Assumptions!D45)
A110: Rev 2034 | B110: =B109*(1+Assumptions!B45) | C110: =C109*(1+Assumptions!C45) | D110: =D109*(1+Assumptions!D45)
A111: Rev 2035 | B111: =B110*(1+Assumptions!B45) | C111: =C110*(1+Assumptions!C45) | D111: =D110*(1+Assumptions!D45)
A112: Rev 2036 | B112: =B111*(1+Assumptions!B46) | C112: =C111*(1+Assumptions!C46) | D112: =D111*(1+Assumptions!D46)
A113: Rev 2037 | B113: =B112*(1+Assumptions!B46) | C113: =C112*(1+Assumptions!C46) | D113: =D112*(1+Assumptions!D46)
A114: Rev 2038 | B114: =B113*(1+Assumptions!B46) | C114: =C113*(1+Assumptions!C46) | D114: =D113*(1+Assumptions!D46)
A115: Rev 2039 | B115: =B114*(1+Assumptions!B46) | C115: =C114*(1+Assumptions!C46) | D115: =D114*(1+Assumptions!D46)
A116: Rev 2040 | B116: =B115*(1+Assumptions!B46) | C116: =C115*(1+Assumptions!C46) | D116: =D115*(1+Assumptions!D46)
A117: Rev 2041 | B117: =B116*(1+Assumptions!B47) | C117: =C116*(1+Assumptions!C47) | D117: =D116*(1+Assumptions!D47)
A118: Rev 2042 | B118: =B117*(1+Assumptions!B47) | C118: =C117*(1+Assumptions!C47) | D118: =D117*(1+Assumptions!D47)
A119: Rev 2043 | B119: =B118*(1+Assumptions!B47) | C119: =C118*(1+Assumptions!C47) | D119: =D118*(1+Assumptions!D47)
A120: Rev 2044 | B120: =B119*(1+Assumptions!B47) | C120: =C119*(1+Assumptions!C47) | D120: =D119*(1+Assumptions!D47)
A121: Rev 2045 | B121: =B120*(1+Assumptions!B47) | C121: =C120*(1+Assumptions!C47) | D121: =D120*(1+Assumptions!D47)
...
